multi_freq_ldpy/__init__.py
multi_freq_ldpy/long_freq_est/L_ADP.py
multi_freq_ldpy/long_freq_est/L_GRR.py
multi_freq_ldpy/long_freq_est/L_OSUE.py
multi_freq_ldpy/long_freq_est/L_OUE.py
multi_freq_ldpy/long_freq_est/L_SOUE.py
multi_freq_ldpy/long_freq_est/L_SUE.py
multi_freq_ldpy/long_freq_est/Variance_LONG_PURE.py
multi_freq_ldpy/long_freq_est/__init__.py
multi_freq_ldpy/long_mdim_freq_est/L_SMP_Solution.py
multi_freq_ldpy/long_mdim_freq_est/L_SPL_Solution.py
multi_freq_ldpy/long_mdim_freq_est/__init__.py
multi_freq_ldpy/mdim_freq_est/RSpFD_solution.py
multi_freq_ldpy/mdim_freq_est/SMP_solution.py
multi_freq_ldpy/mdim_freq_est/SPL_solution.py
multi_freq_ldpy/mdim_freq_est/Variance_RSpFD.py
multi_freq_ldpy/mdim_freq_est/__init__.py
multi_freq_ldpy/pure_frequency_oracles/ADP.py
multi_freq_ldpy/pure_frequency_oracles/GRR.py
multi_freq_ldpy/pure_frequency_oracles/LH.py
multi_freq_ldpy/pure_frequency_oracles/UE.py
multi_freq_ldpy/pure_frequency_oracles/Variance_PURE.py
multi_freq_ldpy/pure_frequency_oracles/__init__.py
multi_freq_ldpy-0.0.2.dist-info/LICENSE.txt
multi_freq_ldpy-0.0.2.dist-info/METADATA
multi_freq_ldpy-0.0.2.dist-info/WHEEL
multi_freq_ldpy-0.0.2.dist-info/top_level.txt
multi_freq_ldpy-0.0.2.dist-info/RECORD
