Metadata-Version: 2.1
Name: multi-freq-ldpy
Version: 0.0.2
Summary: Multiple Frequency Estimation Under Local Differential Privacy in Python
Home-page: https://github.com/hharcolezi/multi-freq-ldpy
Author: Héber H. Arcolezi
Author-email: hh.arcolezi@gmail.com
License: MIT
Keywords: local-differential-privacy
Platform: UNKNOWN
Classifier: Programming Language :: Python :: 3
Classifier: License :: OSI Approved :: MIT License
Classifier: Operating System :: OS Independent
Requires-Python: >=3.6
License-File: LICENSE.txt
Requires-Dist: numpy
Requires-Dist: numba
